budoux/__init__.py
budoux/html_processor.py
budoux/main.py
budoux/parser.py
budoux/py.typed
budoux/skip_nodes.json
budoux/utils.py
budoux/models/ja.json
budoux/models/ja_knbc.json
budoux/models/th.json
budoux/models/zh-hans.json
budoux/models/zh-hant.json
scripts/__init__.py
scripts/build_model.py
scripts/encode_data.py
scripts/finetune.py
scripts/prepare_knbc.py
scripts/prepare_wisesight.py
scripts/train.py
scripts/translate_model.py
budoux-0.7.0.dist-info/LICENSE
budoux-0.7.0.dist-info/METADATA
budoux-0.7.0.dist-info/WHEEL
budoux-0.7.0.dist-info/entry_points.txt
budoux-0.7.0.dist-info/top_level.txt
budoux-0.7.0.dist-info/RECORD
