Metadata-Version: 2.2
Name: budoux
Version: 0.7.0
Summary: BudouX is the successor of Budou
Author: Shuhei Iitsuka
Author-email: tushuhei@google.com
License: Apache-2.0
Classifier: Development Status :: 3 - Alpha
Classifier: Operating System :: OS Independent
Classifier: License :: OSI Approved :: Apache Software License
Classifier: Programming Language :: Python :: 3.9
Classifier: Programming Language :: Python :: 3.10
Classifier: Programming Language :: Python :: 3.11
Classifier: Programming Language :: Python :: 3.12
Classifier: Programming Language :: Python :: 3.13
Requires-Python: >=3.9
License-File: LICENSE
Requires-Dist: importlib-resources
Provides-Extra: dev
Requires-Dist: build; extra == "dev"
Requires-Dist: flake8; extra == "dev"
Requires-Dist: isort; extra == "dev"
Requires-Dist: mypy==1.15.0; extra == "dev"
Requires-Dist: pytest; extra == "dev"
Requires-Dist: regex; extra == "dev"
Requires-Dist: toml; extra == "dev"
Requires-Dist: twine; extra == "dev"
Requires-Dist: types-regex; extra == "dev"
Requires-Dist: types-setuptools; extra == "dev"
Requires-Dist: yapf; extra == "dev"
Provides-Extra: jaxcpu
Requires-Dist: jax==0.5.2; extra == "jaxcpu"
